dj_gcp_iotdevice/__init__.py
dj_gcp_iotdevice/apps.py
dj_gcp_iotdevice/models.py
dj_gcp_iotdevice/serializers.py
dj_gcp_iotdevice/urls.py
dj_gcp_iotdevice/views.py
dj_gcp_iotdevice/migrations/0001_initial.py
dj_gcp_iotdevice/migrations/__init__.py
dj_gcp_iotdevice-0.3.1.dist-info/METADATA
dj_gcp_iotdevice-0.3.1.dist-info/WHEEL
dj_gcp_iotdevice-0.3.1.dist-info/top_level.txt
dj_gcp_iotdevice-0.3.1.dist-info/RECORD
