Metadata-Version: 2.1
Name: dj-gcp-iotdevice
Version: 0.3.1
Summary: App for Django to provide a CRUD REST interface for GCP's IoT Core
Home-page: https://gitlab.com/pennatus/dj_gcp_iotdevice
Author: Steve Graham
Author-email: stgraham2000@gmail.com
License: MIT license
Keywords: dj_gcp_iotdevice
Platform: UNKNOWN
Classifier: Intended Audience :: Developers
Classifier: License :: OSI Approved :: MIT License
Classifier: Natural Language :: English
Classifier: Programming Language :: Python :: 3.4
Classifier: Programming Language :: Python :: 3.5
Classifier: Programming Language :: Python :: 3.6
Classifier: Programming Language :: Python :: 3.7
Classifier: Programming Language :: Python :: 3.8
Requires-Python: >=3.4
Requires-Dist: google-cloud-iot (>=1.0.0)
